[
  {
    "date":1547928000000,
    "temperature":{
      "night":-2,
      "day":-1
    },
    "cloudiness":"Ясно",
    "snow":false,
    "rain":false
  },
  {
    "date":1548014400000,
    "temperature":{
      "night":8,
      "day":9
    },
    "cloudiness":"Облачно",
    "snow":false,
    "rain":false
  },
  {
    "date":1548100800000,
    "temperature":{
      "night":-3,
      "day":-2
    },
    "cloudiness":"Облачно",
    "snow":true,
    "rain":false
  },
  {
    "date":1548187200000,
    "temperature":{
      "night":-6,
      "day":-2
    },
    "cloudiness":"Облачно",
    "snow":true,
    "rain":false
  },
  {
    "date":1548273600000,
    "temperature":{
      "night":8,
      "day":12
    },
    "cloudiness":"Облачно",
    "snow":false,
    "rain":true
  },
  {
    "date":1548360000000,
    "temperature":{
      "night":-7,
      "day":-5
    },
    "cloudiness":"Ясно",
    "snow":false,
    "rain":false
  },
  {
    "date":1548446400000,
    "temperature":{
      "night":-3,
      "day":-2
    },
    "cloudiness":"Ясно",
    "snow":false,
    "rain":false
  },
  {
    "date":1548532800000,
    "temperature":{
      "night":7,
      "day":11
    },
    "cloudiness":"Ясно",
    "snow":false,
    "rain":false
  },
  {
    "date":1548619200000,
    "temperature":{
      "night":-4,
      "day":-2
    },
    "cloudiness":"Ясно",
    "snow":false,
    "rain":false
  },
  {
    "date":1548705600000,
    "temperature":{
      "night":-7,
      "day":-2
    },
    "cloudiness":"Ясно",
    "snow":false,
    "rain":false
  },
  {
    "date":1548792000000,
    "temperature":{
      "night":-10,
      "day":-5
    },
    "cloudiness":"Облачно",
    "snow":true,
    "rain":false
  },
  {
    "date":1548878400000,
    "temperature":{
      "night":-2,
      "day":0
    },
    "cloudiness":"Ясно",
    "snow":false,
    "rain":false
  },
  {
    "date":1548964800000,
    "temperature":{
      "night":9,
      "day":13
    },
    "cloudiness":"Облачно",
    "snow":false,
    "rain":false
  },
  {
    "date":1549051200000,
    "temperature":{
      "night":6,
      "day":9
    },
    "cloudiness":"Облачно",
    "snow":false,
    "rain":false
  },
  {
    "date":1549137600000,
    "temperature":{
      "night":-1,
      "day":2
    },
    "cloudiness":"Облачно",
    "snow":false,
    "rain":true
  },
  {
    "date":1549224000000,
    "temperature":{
      "night":-9,
      "day":-8
    },
    "cloudiness":"Облачно",
    "snow":false,
    "rain":false
  },
  {
    "date":1549310400000,
    "temperature":{
      "night":6,
      "day":8
    },
    "cloudiness":"Облачно",
    "snow":false,
    "rain":false
  },
  {
    "date":1549396800000,
    "temperature":{
      "night":0,
      "day":2
    },
    "cloudiness":"Облачно",
    "snow":false,
    "rain":true
  },
  {
    "date":1549483200000,
    "temperature":{
      "night":2,
      "day":2
    },
    "cloudiness":"Ясно",
    "snow":false,
    "rain":false
  },
  {
    "date":1549569600000,
    "temperature":{
      "night":8,
      "day":12
    },
    "cloudiness":"Облачно",
    "snow":false,
    "rain":true
  },
  {
    "date":1549656000000,
    "temperature":{
      "night":-9,
      "day":-7
    },
    "cloudiness":"Ясно",
    "snow":false,
    "rain":false
  },
  {
    "date":1549742400000,
    "temperature":{
      "night":-7,
      "day":-6
    },
    "cloudiness":"Облачно",
    "snow":false,
    "rain":false
  },
  {
    "date":1549828800000,
    "temperature":{
      "night":0,
      "day":3
    },
    "cloudiness":"Облачно",
    "snow":false,
    "rain":true
  },
  {
    "date":1549915200000,
    "temperature":{
      "night":4,
      "day":5
    },
    "cloudiness":"Облачно",
    "snow":false,
    "rain":true
  },
  {
    "date":1550001600000,
    "temperature":{
      "night":2,
      "day":5
    },
    "cloudiness":"Ясно",
    "snow":false,
    "rain":false
  },
  {
    "date":1550088000000,
    "temperature":{
      "night":4,
      "day":7
    },
    "cloudiness":"Ясно",
    "snow":false,
    "rain":false
  },
  {
    "date":1550174400000,
    "temperature":{
      "night":-2,
      "day":3
    },
    "cloudiness":"Ясно",
    "snow":false,
    "rain":false
  },
  {
    "date":1550260800000,
    "temperature":{
      "night":6,
      "day":8
    },
    "cloudiness":"Облачно",
    "snow":false,
    "rain":true
  },
  {
    "date":1550347200000,
    "temperature":{
      "night":-9,
      "day":-8
    },
    "cloudiness":"Ясно",
    "snow":false,
    "rain":false
  },
  {
    "date":1550433600000,
    "temperature":{
      "night":-9,
      "day":-5
    },
    "cloudiness":"Ясно",
    "snow":false,
    "rain":false
  },
  {
    "date":1550520000000,
    "temperature":{
      "night":-4,
      "day":-1
    },
    "cloudiness":"Ясно",
    "snow":false,
    "rain":false
  }
]